setup.py
dogpile_appengine/__about__.py
dogpile_appengine/__init__.py
dogpile_appengine/backend.py
dogpile_appengine.egg-info/PKG-INFO
dogpile_appengine.egg-info/SOURCES.txt
dogpile_appengine.egg-info/dependency_links.txt
dogpile_appengine.egg-info/entry_points.txt
dogpile_appengine.egg-info/not-zip-safe
dogpile_appengine.egg-info/top_level.txt