Metadata-Version: 1.0
Name: dogpile-appengine
Version: 0.0.2
Summary: dogpile.cache backend for Memcache on Google AppEngine
Home-page: UNKNOWN
Author: David Adrian
Author-email: davidcadrian@gmail.com
License: Apache License, Version 2.0
Keywords: python dogpile memcache backend appengine
Platform: UNKNOWN
